temporal/__init__.py
temporal-1.0.0.dist-info/DESCRIPTION.rst
temporal-1.0.0.dist-info/METADATA
temporal-1.0.0.dist-info/RECORD
temporal-1.0.0.dist-info/WHEEL
temporal-1.0.0.dist-info/metadata.json
temporal-1.0.0.dist-info/top_level.txt
