Metadata-Version: 2.0
Name: temporal
Version: 1.0.0
Summary: Track Django temporal models.
Home-page: UNKNOWN
Author: JamshedVesuna
Author-email: jvesuna314@gmail.com
License: UNKNOWN
Platform: UNKNOWN
